test-files/configs/basic/targets/benchmark_tokio.py
test-files/configs/inherit/targets/benchmark_smol.py
tests/__init__.py
tests/test_benchmark.py
tests/test_cluster.py
tests/test_cmd.py
tests/test_config.py
tests/test_experiment.py
wke/__init__.py
wke/cluster.py
wke/config.py
wke/errors.py
wke/logging.py
wke/machines.py
wke/plot_loads.py
wke/py.typed
wke/reboot.py
wke/run.py
wke/set.py
wke/slice.py
wke/tasks.py
wke/util.py
wke/benchmark/__init__.py
wke/benchmark/params.py
wke/benchmark/plot.py
wke/benchmark/printer.py
wke/benchmark/toml.py
wke/bin/__init__.py
wke/bin/cmd.py
wke/measurement/__init__.py
wke/measurement/data_collector.py
wke/measurement/sockets.py
wke-0.1.dist-info/LICENSE
wke-0.1.dist-info/METADATA
wke-0.1.dist-info/WHEEL
wke-0.1.dist-info/entry_points.txt
wke-0.1.dist-info/top_level.txt
wke-0.1.dist-info/RECORD
