Metadata-Version: 2.1
Name: wke
Version: 0.1
Project-URL: Homepage, https://github.com/kaimast/wke
Project-URL: Issues, https://github.com/kaimast/wke/issues
Classifier: Programming Language :: Python :: 3
Classifier: License :: OSI Approved :: MIT License
Requires-Python: >=3.11
License-File: LICENSE
Requires-Dist: paramiko
Requires-Dist: pandas
Requires-Dist: seaborn
